qutree/__init__.py
qutree/benchmark_functions.py
qutree/convenience.py
qutree/internal_coordinates.py
qutree/matrix_completion.py
qutree/matrix_factorizations/__init__.py
qutree/matrix_factorizations/maxvol.py
qutree/matrix_factorizations/simul_diag.py
qutree/matrix_factorizations/simultaneous_diagonalization.py
qutree/optimization.py
qutree/plot.py
qutree/ttn/__init__.py
qutree/ttn/grid.py
qutree/ttn/network.py
qutree/ttn/tensor.py
qutree/ttn/tensor_network.py
qutree/ttn/ttnopt.py
pyqutree-0.1.5.dist-info/METADATA
pyqutree-0.1.5.dist-info/WHEEL
pyqutree-0.1.5.dist-info/RECORD
