Metadata-Version: 2.1
Name: pyqutree
Version: 0.1.5
Summary: QuTree: A tree tensor network package
License: BSD-3-Clause
Keywords: tensor network,chemistry,optimization,cross approximation
Author: Roman Ellerbrock
Author-email: romanellerbrock@gmail.com
Requires-Python: >=3.10,<4.0
Classifier: Development Status :: 3 - Alpha
Classifier: Intended Audience :: Science/Research
Classifier: License :: OSI Approved :: BSD License
Classifier: Operating System :: OS Independent
Classifier: Programming Language :: Python :: 3
Classifier: Programming Language :: Python :: 3.10
Classifier: Programming Language :: Python :: 3.11
Classifier: Programming Language :: Python :: 3.12
Classifier: Topic :: Scientific/Engineering
Classifier: Topic :: Scientific/Engineering :: Chemistry
Classifier: Topic :: Scientific/Engineering :: Mathematics
Classifier: Topic :: Scientific/Engineering :: Physics
Requires-Dist: imageio (>=2.9)
Requires-Dist: matplotlib (>=3.5)
Requires-Dist: networkx (>=2.6)
Requires-Dist: numpy (>=1.20)
Requires-Dist: pandas (>=2.0)
Requires-Dist: plotly (>=5.0)
Requires-Dist: pydot (>=1.4)
Requires-Dist: pyscf (>=2.0)
Requires-Dist: scipy (>=1.7)
Requires-Dist: tqdm (>=4.60)
Project-URL: Bug Tracker, https://github.com/roman-ellerbrock/pyqutree/issues
Project-URL: Documentation, https://pyqutree-ttn.readthedocs.io
Project-URL: Homepage, https://github.com/roman-ellerbrock/pyqutree
Project-URL: Paper, https://doi.org/10.1063/5.0180233
Project-URL: Repository, https://github.com/roman-ellerbrock/pyqutree
